pynimbar/__init__.py
pynimbar/pynimbar.py
pynimbar-1.1.1.dist-info/LICENSE
pynimbar-1.1.1.dist-info/METADATA
pynimbar-1.1.1.dist-info/WHEEL
pynimbar-1.1.1.dist-info/top_level.txt
pynimbar-1.1.1.dist-info/RECORD
