Metadata-Version: 2.1
Name: pynimbar
Version: 1.1.1
Summary: Make your Python scripts more user friendly with loading animations
Author-email: Gabriel Mitelman Tkacz <gmtkacz@proton.me>
Maintainer-email: Gabriel Mitelman Tkacz <gmtkacz@proton.me>
License: MIT License
Project-URL: Repository, https://github.com/gtkacz/pynimbar.git
Project-URL: Issues, https://github.com/gtkacz/pynimbar/issues
Keywords: animation,context manager,error handling
Classifier: Development Status :: 5 - Production/Stable
Classifier: Intended Audience :: Developers
Classifier: License :: OSI Approved :: MIT License
Classifier: Programming Language :: Python :: 3
Classifier: Programming Language :: Python :: 3.6
Classifier: Programming Language :: Python :: 3.7
Classifier: Programming Language :: Python :: 3.8
Classifier: Programming Language :: Python :: 3.9
Classifier: Programming Language :: Python :: 3.10
Classifier: Programming Language :: Python :: 3.11
Classifier: Programming Language :: Python :: 3.12
Requires-Python: >=3.6
License-File: LICENSE
